rawket/__init__.py
rawket-0.0.1.dist-info/LICENSE
rawket-0.0.1.dist-info/METADATA
rawket-0.0.1.dist-info/WHEEL
rawket-0.0.1.dist-info/RECORD
